{"v":"5.5.10","fr":60,"ip":0,"op":180,"w":3000,"h":3000,"nm":"玛莎拉蒂-全","ddd":0,"assets":[{"id":"comp_0","layers":[{"ddd":0,"ind":1,"ty":4,"nm":"corner mask 2","td":1,"sr":1,"ks":{"p":{"a":0,"k":[1510.34,1648.141,0]},"a":{"a":0,"k":[10.34,134.141,0]},"s":{"a":0,"k":[100,102.289,100]}},"ao":0,"shapes":[{"ty":"gr","it":[{"ty":"rc","d":1,"s":{"a":0,"k":[748.68,524.141]},"p":{"a":0,"k":[0,0]},"r":{"a":0,"k":0},"nm":"Rectangle Path 1","hd":false},{"ty":"gf","o":{"a":0,"k":100},"r":1,"bm":0,"g":{"p":3,"k":{"a":0,"k":[0,0.161,0.161,0.161,0.5,0.161,0.161,0.161,1,0.161,0.161,0.161]}},"s":{"a":0,"k":[0,0]},"e":{"a":0,"k":[100,0]},"t":1,"nm":"Gradient Fill 1","hd":false},{"ty":"tr","p":{"a":0,"k":[10.34,-127.93]},"a":{"a":0,"k":[0,0]},"s":{"a":0,"k":[100,100]},"r":{"a":0,"k":0},"o":{"a":0,"k":100},"sk":{"a":0,"k":0},"sa":{"a":0,"k":0},"nm":"Transform"}],"nm":"Rectangle 1","bm":0,"hd":false}],"ip":0,"op":19800,"st":0,"bm":0},{"ddd":0,"ind":2,"ty":4,"nm":"right up corner","tt":1,"sr":1,"ks":{"r":{"a":1,"k":[{"i":{"x":[0.21],"y":[1]},"o":{"x":[0.082],"y":[0]},"t":5,"s":[-25]},{"t":40,"s":[0]}]},"p":{"a":1,"k":[{"i":{"x":0.21,"y":1},"o":{"x":0.082,"y":0},"t":5,"s":[1545.027,2165.966,0],"to":[10,-86.667,0],"ti":[-10,86.667,0]},{"t":40,"s":[1605.027,1645.966,0]}]},"a":{"a":0,"k":[1641.027,1649.966,0]}},"ao":0,"shapes":[{"ty":"gr","it":[{"ind":0,"ty":"sh","ks":{"a":0,"k":{"i":[[-24.29,-0.749],[5.217,-147.892],[0,0],[-70.336,100.135],[13.58,-2.926]],"o":[[-99.784,114.977],[0,0],[12.412,-118.574],[-14.639,3.154],[8.553,-20.853]],"v":[[102.409,-198.375],[-42.134,199.125],[-102.409,199.125],[15.932,-128.983],[-24.351,-120.303]],"c":true}},"nm":"Path 1","hd":false},{"ty":"fl","c":{"a":0,"k":[1,1,1,1]},"o":{"a":0,"k":100},"r":1,"bm":0,"nm":"Fill 1","hd":false},{"ty":"tr","p":{"a":0,"k":[1743.436,1450.842]},"a":{"a":0,"k":[0,0]},"s":{"a":0,"k":[100,100]},"r":{"a":0,"k":0},"o":{"a":0,"k":100},"sk":{"a":0,"k":0},"sa":{"a":0,"k":0},"nm":"Transform"}],"nm":"Group 9","bm":0,"hd":false}],"ip":0,"op":19800,"st":0,"bm":0},{"ddd":0,"ind":3,"ty":4,"nm":"corner mask 2","td":1,"sr":1,"ks":{"p":{"a":0,"k":[1510.34,1648.141,0]},"a":{"a":0,"k":[10.34,134.141,0]},"s":{"a":0,"k":[100,102.289,100]}},"ao":0,"shapes":[{"ty":"gr","it":[{"ty":"rc","d":1,"s":{"a":0,"k":[748.68,524.141]},"p":{"a":0,"k":[0,0]},"r":{"a":0,"k":0},"nm":"Rectangle Path 1","hd":false},{"ty":"gf","o":{"a":0,"k":100},"r":1,"bm":0,"g":{"p":3,"k":{"a":0,"k":[0,0.161,0.161,0.161,0.5,0.161,0.161,0.161,1,0.161,0.161,0.161]}},"s":{"a":0,"k":[0,0]},"e":{"a":0,"k":[100,0]},"t":1,"nm":"Gradient Fill 1","hd":false},{"ty":"tr","p":{"a":0,"k":[10.34,-127.93]},"a":{"a":0,"k":[0,0]},"s":{"a":0,"k":[100,100]},"r":{"a":0,"k":0},"o":{"a":0,"k":100},"sk":{"a":0,"k":0},"sa":{"a":0,"k":0},"nm":"Transform"}],"nm":"Rectangle 1","bm":0,"hd":false}],"ip":0,"op":19800,"st":0,"bm":0},{"ddd":0,"ind":4,"ty":4,"nm":"left up corner","tt":1,"sr":1,"ks":{"r":{"a":1,"k":[{"i":{"x":[0.21],"y":[1]},"o":{"x":[0.082],"y":[0]},"t":5,"s":[25]},{"t":40,"s":[0]}]},"p":{"a":1,"k":[{"i":{"x":0.21,"y":1},"o":{"x":0.082,"y":0},"t":5,"s":[1456.395,2167.003,0],"to":[-10,-86.667,0],"ti":[10,86.667,0]},{"t":40,"s":[1396.395,1647.003,0]}]},"a":{"a":0,"k":[1432.395,1651.003,0]}},"ao":0,"shapes":[{"ty":"gr","it":[{"ind":0,"ty":"sh","ks":{"a":0,"k":{"i":[[-11.044,-23.185],[14.727,3.098],[-12.352,-119.795],[9.705,0],[10.502,0],[99.153,113.856]],"o":[[-13.689,-2.879],[69.859,99.71],[-10.747,0],[-9.77,0],[-5.274,-148.403],[18.96,-4.289]],"v":[[24.17,-119.64],[-16.183,-128.128],[101.994,200.876],[71.837,200.877],[41.797,200.876],[-101.994,-196.588]],"c":true}},"nm":"Path 1","hd":false},{"ty":"fl","c":{"a":0,"k":[1,1,1,1]},"o":{"a":0,"k":100},"r":1,"bm":0,"nm":"Fill 1","hd":false},{"ty":"tr","p":{"a":0,"k":[1330.402,1450.126]},"a":{"a":0,"k":[0,0]},"s":{"a":0,"k":[100,100]},"r":{"a":0,"k":0},"o":{"a":0,"k":100},"sk":{"a":0,"k":0},"sa":{"a":0,"k":0},"nm":"Transform"}],"nm":"Group 10","bm":0,"hd":false}],"ip":0,"op":19800,"st":0,"bm":0},{"ddd":0,"ind":5,"ty":4,"nm":"corner mask 2","td":1,"sr":1,"ks":{"p":{"a":0,"k":[1510.34,1648.141,0]},"a":{"a":0,"k":[10.34,134.141,0]},"s":{"a":0,"k":[100,102.289,100]}},"ao":0,"shapes":[{"ty":"gr","it":[{"ty":"rc","d":1,"s":{"a":0,"k":[748.68,524.141]},"p":{"a":0,"k":[0,0]},"r":{"a":0,"k":0},"nm":"Rectangle Path 1","hd":false},{"ty":"gf","o":{"a":0,"k":100},"r":1,"bm":0,"g":{"p":3,"k":{"a":0,"k":[0,0.161,0.161,0.161,0.5,0.161,0.161,0.161,1,0.161,0.161,0.161]}},"s":{"a":0,"k":[0,0]},"e":{"a":0,"k":[100,0]},"t":1,"nm":"Gradient Fill 1","hd":false},{"ty":"tr","p":{"a":0,"k":[10.34,-127.93]},"a":{"a":0,"k":[0,0]},"s":{"a":0,"k":[100,100]},"r":{"a":0,"k":0},"o":{"a":0,"k":100},"sk":{"a":0,"k":0},"sa":{"a":0,"k":0},"nm":"Transform"}],"nm":"Rectangle 1","bm":0,"hd":false}],"ip":0,"op":19800,"st":0,"bm":0},{"ddd":0,"ind":6,"ty":4,"nm":"middle corner","tt":1,"sr":1,"ks":{"r":{"a":1,"k":[{"i":{"x":[0.21],"y":[1]},"o":{"x":[0.082],"y":[0]},"t":5,"s":[0]},{"t":40,"s":[0]}]},"p":{"a":1,"k":[{"i":{"x":0.21,"y":1},"o":{"x":0.082,"y":0},"t":5,"s":[1501.113,1936.077,0],"to":[0,-93.333,0],"ti":[0,93.333,0]},{"t":40,"s":[1501.113,1376.077,0]}]},"a":{"a":0,"k":[1537.113,1380.077,0]}},"ao":0,"shapes":[{"ty":"gr","it":[{"ind":0,"ty":"sh","ks":{"a":0,"k":{"i":[[0,0],[-14.095,-23.717],[12.958,5.936],[-0.745,-22.306],[-19.876,-76.223],[-14.368,-39.183],[-2.481,-5.409],[16.508,0.741],[1.11,3.269],[9.563,29.209],[1.591,4.755],[7.401,-22.691],[37.375,0.001],[6.73,0],[-9.132,23.556],[-4.559,58.172],[-3.271,60.23],[0,4.485],[16.219,-7.45],[-9.782,21.556],[-7.081,21.786]],"o":[[9.663,21.311],[-16.089,-7.371],[0,22.717],[2.622,78.405],[10.483,40.202],[1.246,3.398],[-18.009,0],[-2.613,-0.117],[-9.881,-29.1],[-0.848,-2.592],[-7.734,25.034],[-11.57,35.48],[-6.093,0],[10.249,-24.332],[21.262,-54.839],[4.711,-60.118],[0.133,-2.436],[-15.258,7.01],[14.011,-23.695],[9.593,-21.137],[0,0]],"v":[[21.85,-204.651],[59.479,-140.222],[16.851,-159.752],[16.964,-92.376],[42.484,140.905],[84.781,258.678],[90.254,270.699],[39.18,270.323],[31.871,262.238],[3.003,174.673],[-0.316,164.744],[-22.209,235.368],[-71.339,270.787],[-90.253,270.787],[-60.498,199.824],[-25.397,29.24],[-15.222,-151.423],[-15.205,-160.792],[-60.101,-140.167],[-22.371,-205.086],[-0.333,-271.065]],"c":false}},"nm":"Path 1","hd":false},{"ty":"fl","c":{"a":0,"k":[1,1,1,1]},"o":{"a":0,"k":100},"r":1,"bm":0,"nm":"Fill 1","hd":false},{"ty":"tr","p":{"a":0,"k":[1537.113,1380.215]},"a":{"a":0,"k":[0,0]},"s":{"a":0,"k":[100,100]},"r":{"a":0,"k":0},"o":{"a":0,"k":100},"sk":{"a":0,"k":0},"sa":{"a":0,"k":0},"nm":"Transform"}],"nm":"Group 11","bm":0,"hd":false}],"ip":0,"op":19800,"st":0,"bm":0},{"ddd":0,"ind":7,"ty":4,"nm":"corner mask","td":1,"sr":1,"ks":{"p":{"a":0,"k":[1498.301,1760,0]},"a":{"a":0,"k":[-1.699,254,0]}},"ao":0,"shapes":[{"ty":"gr","it":[{"ty":"rc","d":1,"s":{"a":0,"k":[440.602,97.93]},"p":{"a":0,"k":[0,0]},"r":{"a":0,"k":0},"nm":"Rectangle Path 1","hd":false},{"ty":"st","c":{"a":0,"k":[1,1,1,1]},"o":{"a":0,"k":100},"w":{"a":0,"k":2},"lc":1,"lj":1,"ml":4,"bm":0,"nm":"Stroke 1","hd":false},{"ty":"gf","o":{"a":0,"k":100},"r":1,"bm":0,"g":{"p":3,"k":{"a":0,"k":[0,0.161,0.161,0.161,0.5,0.161,0.161,0.161,1,0.161,0.161,0.161]}},"s":{"a":0,"k":[0,0]},"e":{"a":0,"k":[100,0]},"t":1,"nm":"Gradient Fill 1","hd":false},{"ty":"tr","p":{"a":0,"k":[-1.699,302.965]},"a":{"a":0,"k":[0,0]},"s":{"a":0,"k":[100,100]},"r":{"a":0,"k":0},"o":{"a":0,"k":100},"sk":{"a":0,"k":0},"sa":{"a":0,"k":0},"nm":"Transform"}],"nm":"Rectangle 1","bm":0,"hd":false}],"ip":0,"op":19800,"st":0,"bm":0},{"ddd":0,"ind":8,"ty":4,"nm":"right down corner","tt":1,"sr":1,"ks":{"r":{"a":1,"k":[{"i":{"x":[0.12],"y":[1]},"o":{"x":[0.03],"y":[0]},"t":5,"s":[20]},{"t":40,"s":[0]}]},"p":{"a":1,"k":[{"i":{"x":0.12,"y":1},"o":{"x":0.03,"y":0},"t":5,"s":[1609.742,1705.817,0],"to":[6.667,16.667,0],"ti":[-6.667,-16.667,0]},{"t":40,"s":[1649.742,1805.817,0]}]},"a":{"a":0,"k":[1685.742,1809.817,0]}},"ao":0,"shapes":[{"ty":"gr","it":[{"ind":0,"ty":"sh","ks":{"a":0,"k":{"i":[[-26.953,-19.821],[6.564,28.783],[0,0],[-12.486,-8.464]],"o":[[-7.082,-31.056],[0,0],[-1.306,12.832],[25.635,17.376]],"v":[[45.135,43.996],[25.068,-43.996],[-43.828,-43.996],[-31.953,-12.251]],"c":true}},"nm":"Path 1","hd":false},{"ty":"fl","c":{"a":0,"k":[1,1,1,1]},"o":{"a":0,"k":100},"r":1,"bm":0,"nm":"Fill 1","hd":false},{"ty":"tr","p":{"a":0,"k":[1685.323,1809.817]},"a":{"a":0,"k":[0,0]},"s":{"a":0,"k":[100,100]},"r":{"a":0,"k":0},"o":{"a":0,"k":100},"sk":{"a":0,"k":0},"sa":{"a":0,"k":0},"nm":"Transform"}],"nm":"Group 1","bm":0,"hd":false}],"ip":0,"op":19800,"st":0,"bm":0},{"ddd":0,"ind":9,"ty":4,"nm":"corner mask","td":1,"sr":1,"ks":{"p":{"a":0,"k":[1498.301,1760,0]},"a":{"a":0,"k":[-1.699,254,0]}},"ao":0,"shapes":[{"ty":"gr","it":[{"ty":"rc","d":1,"s":{"a":0,"k":[440.602,97.93]},"p":{"a":0,"k":[0,0]},"r":{"a":0,"k":0},"nm":"Rectangle Path 1","hd":false},{"ty":"st","c":{"a":0,"k":[1,1,1,1]},"o":{"a":0,"k":100},"w":{"a":0,"k":2},"lc":1,"lj":1,"ml":4,"bm":0,"nm":"Stroke 1","hd":false},{"ty":"gf","o":{"a":0,"k":100},"r":1,"bm":0,"g":{"p":3,"k":{"a":0,"k":[0,0.161,0.161,0.161,0.5,0.161,0.161,0.161,1,0.161,0.161,0.161]}},"s":{"a":0,"k":[0,0]},"e":{"a":0,"k":[100,0]},"t":1,"nm":"Gradient Fill 1","hd":false},{"ty":"tr","p":{"a":0,"k":[-1.699,302.965]},"a":{"a":0,"k":[0,0]},"s":{"a":0,"k":[100,100]},"r":{"a":0,"k":0},"o":{"a":0,"k":100},"sk":{"a":0,"k":0},"sa":{"a":0,"k":0},"nm":"Transform"}],"nm":"Rectangle 1","bm":0,"hd":false}],"ip":0,"op":19800,"st":0,"bm":0},{"ddd":0,"ind":10,"ty":4,"nm":"left down corner","tt":1,"sr":1,"ks":{"r":{"a":1,"k":[{"i":{"x":[0.18],"y":[1]},"o":{"x":[0.03],"y":[0]},"t":5,"s":[-20]},{"t":40,"s":[0]}]},"p":{"a":1,"k":[{"i":{"x":0.18,"y":1},"o":{"x":0.03,"y":0},"t":5,"s":[1405.207,1641.821,0],"to":[-1.333,20,0],"ti":[1.333,-20,0]},{"t":40,"s":[1397.207,1761.821,0]}]},"a":{"a":0,"k":[1433.207,1765.821,0]}},"ao":0,"shapes":[{"ty":"gr","it":[{"ind":0,"ty":"sh","ks":{"a":0,"k":{"i":[[26.953,-19.821],[-6.564,28.783],[0,0],[12.487,-8.464]],"o":[[7.083,-31.056],[0,0],[1.306,12.832],[-25.635,17.376]],"v":[[-45.135,43.996],[-25.068,-43.996],[43.829,-43.996],[31.953,-12.251]],"c":true}},"nm":"Path 1","hd":false},{"ty":"fl","c":{"a":0,"k":[1,1,1,1]},"o":{"a":0,"k":100},"r":1,"bm":0,"nm":"Fill 1","hd":false},{"ty":"tr","p":{"a":0,"k":[1388.91,1809.817]},"a":{"a":0,"k":[0,0]},"s":{"a":0,"k":[100,100]},"r":{"a":0,"k":0},"o":{"a":0,"k":100},"sk":{"a":0,"k":0},"sa":{"a":0,"k":0},"nm":"Transform"}],"nm":"Group 4","bm":0,"hd":false}],"ip":0,"op":19800,"st":0,"bm":0},{"ddd":0,"ind":11,"ty":4,"nm":"bars","sr":1,"ks":{"p":{"a":0,"k":[1500.344,1703.988,0]},"a":{"a":0,"k":[1536.344,1707.988,0]}},"ao":0,"shapes":[{"ty":"gr","it":[{"ind":0,"ty":"sh","ks":{"a":0,"k":{"i":[[0,0],[0,0],[0,0],[0,0]],"o":[[0,0],[0,0],[0,0],[0,0]],"v":[[-210.106,-12.196],[210.105,-12.196],[210.105,12.196],[-210.106,12.196]],"c":true}},"nm":"Path 1","hd":false},{"ty":"fl","c":{"a":0,"k":[1,1,1,1]},"o":{"a":0,"k":100},"r":1,"bm":0,"nm":"Fill 1","hd":false},{"ty":"tr","p":{"a":0,"k":[1536.342,1743.727]},"a":{"a":0,"k":[0,0]},"s":{"a":1,"k":[{"i":{"x":[0.008,0.008],"y":[1,1]},"o":{"x":[0.075,0.075],"y":[0,0]},"t":0,"s":[5,100]},{"t":35,"s":[100,100]}]},"r":{"a":0,"k":0},"o":{"a":0,"k":100},"sk":{"a":0,"k":0},"sa":{"a":0,"k":0},"nm":"Transform"}],"nm":"Group 6","bm":0,"hd":false},{"ty":"gr","it":[{"ind":0,"ty":"sh","ks":{"a":0,"k":{"i":[[0,0],[0,0],[0,0],[0,0]],"o":[[0,0],[0,0],[0,0],[0,0]],"v":[[-210.12,-12.107],[210.12,-12.107],[210.12,12.106],[-210.12,12.106]],"c":true}},"nm":"Path 1","hd":false},{"ty":"fl","c":{"a":0,"k":[1,1,1,1]},"o":{"a":0,"k":100},"r":1,"bm":0,"nm":"Fill 1","hd":false},{"ty":"tr","p":{"a":0,"k":[1536.308,1707.893]},"a":{"a":0,"k":[0,0]},"s":{"a":1,"k":[{"i":{"x":[0.008,0.008],"y":[1,1]},"o":{"x":[0.075,0.075],"y":[0,0]},"t":2,"s":[5,100]},{"t":37,"s":[100,100]}]},"r":{"a":0,"k":0},"o":{"a":0,"k":100},"sk":{"a":0,"k":0},"sa":{"a":0,"k":0},"nm":"Transform"}],"nm":"Group 7","bm":0,"hd":false},{"ty":"gr","it":[{"ind":0,"ty":"sh","ks":{"a":0,"k":{"i":[[0,0],[0,0],[0,0],[0,0]],"o":[[0,0],[0,0],[0,0],[0,0]],"v":[[209.895,12.161],[-209.895,12.161],[-209.895,-12.161],[209.895,-12.161]],"c":true}},"nm":"Path 1","hd":false},{"ty":"fl","c":{"a":0,"k":[1,1,1,1]},"o":{"a":0,"k":100},"r":1,"bm":0,"nm":"Fill 1","hd":false},{"ty":"tr","p":{"a":0,"k":[1536.606,1672.214]},"a":{"a":0,"k":[0,0]},"s":{"a":1,"k":[{"i":{"x":[0.008,0.008],"y":[1,1]},"o":{"x":[0.075,0.075],"y":[0,0]},"t":4,"s":[5,100]},{"t":39,"s":[100,100]}]},"r":{"a":0,"k":0},"o":{"a":0,"k":100},"sk":{"a":0,"k":0},"sa":{"a":0,"k":0},"nm":"Transform"}],"nm":"Group 8","bm":0,"hd":false}],"ip":0,"op":19800,"st":0,"bm":0},{"ddd":0,"ind":12,"ty":4,"nm":"bottom","sr":1,"ks":{"p":{"a":0,"k":[1500.685,1850.611,0]},"a":{"a":0,"k":[1536.685,1854.611,0]}},"ao":0,"shapes":[{"ty":"gr","it":[{"ind":0,"ty":"sh","ks":{"a":0,"k":{"i":[[0,0],[0,0],[0,0],[-0.936,17.899]],"o":[[0,0],[0,0],[0.863,-16.5],[0,0]],"v":[[38.4,-25.198],[40.288,25.198],[-40.288,25.198],[-37.643,-25.198]],"c":true}},"nm":"Path 1","hd":false},{"ty":"fl","c":{"a":0,"k":[1,1,1,1]},"o":{"a":0,"k":100},"r":1,"bm":0,"nm":"Fill 1","hd":false},{"ty":"tr","p":{"a":0,"k":[1535.779,1916.444]},"a":{"a":0,"k":[0,0]},"s":{"a":0,"k":[100,100]},"r":{"a":0,"k":0},"o":{"a":0,"k":100},"sk":{"a":0,"k":0},"sa":{"a":0,"k":0},"nm":"Transform"}],"nm":"Group 2","bm":0,"hd":false},{"ty":"gr","it":[{"ind":0,"ty":"sh","ks":{"a":0,"k":{"i":[[0,0],[0,0],[0,0],[0,0]],"o":[[0,0],[0,0],[0,0],[0,0]],"v":[[-61.017,-12.289],[61.017,-12.289],[61.017,12.288],[-61.017,12.288]],"c":true}},"nm":"Path 1","hd":false},{"ty":"fl","c":{"a":0,"k":[1,1,1,1]},"o":{"a":0,"k":100},"r":1,"bm":0,"nm":"Fill 1","hd":false},{"ty":"tr","p":{"a":0,"k":[1536.64,1869.602]},"a":{"a":0,"k":[0,0]},"s":{"a":0,"k":[100,100]},"r":{"a":0,"k":0},"o":{"a":0,"k":100},"sk":{"a":0,"k":0},"sa":{"a":0,"k":0},"nm":"Transform"}],"nm":"Group 3","bm":0,"hd":false},{"ty":"gr","it":[{"ind":0,"ty":"sh","ks":{"a":0,"k":{"i":[[0,0],[-0.201,-4.373],[5.916,-31.386],[0,0],[43.582,2.258],[-0.044,1.96],[-0.313,2.652]],"o":[[0.197,4.297],[-43.057,2.901],[0,0],[-6.583,-30.381],[-0.179,-2.374],[0.043,-1.976],[0,0]],"v":[[87.279,-39.976],[87.855,-27.404],[36.296,39.975],[-36.057,39.975],[-87.38,-27.078],[-87.812,-33.38],[-87.073,-39.976]],"c":true}},"nm":"Path 1","hd":false},{"ty":"fl","c":{"a":0,"k":[1,1,1,1]},"o":{"a":0,"k":100},"r":1,"bm":0,"nm":"Fill 1","hd":false},{"ty":"tr","p":{"a":0,"k":[1536.665,1807.555]},"a":{"a":0,"k":[0,0]},"s":{"a":0,"k":[100,100]},"r":{"a":0,"k":0},"o":{"a":0,"k":100},"sk":{"a":0,"k":0},"sa":{"a":0,"k":0},"nm":"Transform"}],"nm":"Group 5","bm":0,"hd":false}],"ip":0,"op":19800,"st":0,"bm":0}]}],"layers":[{"ddd":0,"ind":1,"ty":4,"nm":"logo mask","parent":7,"td":1,"sr":1,"ks":{"p":{"a":0,"k":[246,527,0]},"a":{"a":0,"k":[1544,2320,0]}},"ao":0,"shapes":[{"ty":"gr","it":[{"ind":0,"ty":"sh","ks":{"a":0,"k":{"i":[[89.856,-89.856],[-179.647,-179.402],[0,0],[0,0],[179.646,179.647],[179.647,-179.401],[117.62,0.002]],"o":[[-179.647,179.647],[0,0],[0,0],[179.646,-179.402],[-179.401,-179.402],[-89.79,-89.668],[-117.706,-0.002]],"v":[[-650.176,-560.844],[-650.176,89.456],[0.122,740.489],[650.178,89.456],[650.178,-560.844],[0.122,-561.089],[-324.907,-695.609]],"c":true}},"nm":"path","hd":false},{"ty":"gf","o":{"a":0,"k":100},"r":1,"bm":0,"g":{"p":3,"k":{"a":0,"k":[0,0.161,0.161,0.161,0.5,0.161,0.161,0.161,1,0.161,0.161,0.161]}},"s":{"a":0,"k":[0,741.094]},"e":{"a":0,"k":[-1.859,-688.391]},"t":1,"nm":"Gradient","hd":false},{"ty":"tr","p":{"a":0,"k":[1538.377,2323.593]},"a":{"a":0,"k":[-3.016,739.344]},"s":{"a":1,"k":[{"i":{"x":[0.058,0.058],"y":[1,1]},"o":{"x":[0.183,0.183],"y":[0,0]},"t":0,"s":[7.68,7.68]},{"i":{"x":[0.915,0.915],"y":[1,1]},"o":{"x":[0.167,0.167],"y":[0,0]},"t":40,"s":[100,100]},{"i":{"x":[0.915,0.915],"y":[1,1]},"o":{"x":[0.764,0.764],"y":[0,0]},"t":50,"s":[100,100]},{"t":80,"s":[7.68,7.68]}]},"r":{"a":0,"k":0},"o":{"a":0,"k":100},"sk":{"a":0,"k":0},"sa":{"a":0,"k":0},"nm":"Transform"}],"nm":"heart dragon","bm":0,"hd":false}],"ip":2,"op":80,"st":-2,"bm":0},{"ddd":0,"ind":2,"ty":0,"nm":"logo","tt":1,"refId":"comp_0","sr":1,"ks":{"p":{"a":1,"k":[{"i":{"x":0.09,"y":1},"o":{"x":0.037,"y":0},"t":0,"s":[1500,2940,0],"to":[0,-240,0],"ti":[0,240,0]},{"i":{"x":0.955,"y":0.955},"o":{"x":0.037,"y":0.037},"t":40,"s":[1500,1500,0],"to":[0,0,0],"ti":[0,0,0]},{"i":{"x":0.955,"y":1},"o":{"x":0.835,"y":0},"t":50,"s":[1500,1500,0],"to":[0,240,0],"ti":[0,-240,0]},{"t":80,"s":[1500,2940,0]}]},"a":{"a":0,"k":[1500,1500,0]},"s":{"a":1,"k":[{"i":{"x":[0.09,0.09,0.09],"y":[1,1,1]},"o":{"x":[0.037,0.037,0.037],"y":[0,0,0]},"t":0,"s":[30,30,100]},{"i":{"x":[0.955,0.955,0.955],"y":[1,1,1]},"o":{"x":[0.037,0.037,0.037],"y":[0,0,0]},"t":40,"s":[100,100,100]},{"i":{"x":[0.955,0.955,0.955],"y":[1,1,1]},"o":{"x":[0.835,0.835,0.835],"y":[0,0,0]},"t":50,"s":[100,100,100]},{"t":80,"s":[30,30,100]}]}},"ao":0,"w":3000,"h":3000,"ip":0,"op":19800,"st":0,"bm":0},{"ddd":0,"ind":3,"ty":4,"nm":"mountain1 mask","parent":7,"td":1,"sr":1,"ks":{"p":{"a":0,"k":[246,527,0]},"a":{"a":0,"k":[1544,2320,0]}},"ao":0,"shapes":[{"ty":"gr","it":[{"ind":0,"ty":"sh","ks":{"a":0,"k":{"i":[[89.856,-89.856],[-179.647,-179.402],[0,0],[0,0],[179.646,179.647],[179.647,-179.401],[117.62,0.002]],"o":[[-179.647,179.647],[0,0],[0,0],[179.646,-179.402],[-179.401,-179.402],[-89.79,-89.668],[-117.706,-0.002]],"v":[[-650.176,-560.844],[-650.176,89.456],[0.122,740.489],[650.178,89.456],[650.178,-560.844],[0.122,-561.089],[-324.907,-695.609]],"c":true}},"nm":"path","hd":false},{"ty":"gf","o":{"a":0,"k":100},"r":1,"bm":0,"g":{"p":3,"k":{"a":0,"k":[0,0.161,0.161,0.161,0.5,0.161,0.161,0.161,1,0.161,0.161,0.161]}},"s":{"a":0,"k":[0,741.094]},"e":{"a":0,"k":[-1.859,-688.391]},"t":1,"nm":"Gradient","hd":false},{"ty":"tr","p":{"a":0,"k":[1538.377,2323.593]},"a":{"a":0,"k":[-3.016,739.344]},"s":{"a":1,"k":[{"i":{"x":[0.058,0.058],"y":[1,1]},"o":{"x":[0.183,0.183],"y":[0,0]},"t":0,"s":[7.68,7.68]},{"i":{"x":[0.915,0.915],"y":[1,1]},"o":{"x":[0.167,0.167],"y":[0,0]},"t":40,"s":[100,100]},{"i":{"x":[0.915,0.915],"y":[1,1]},"o":{"x":[0.764,0.764],"y":[0,0]},"t":50,"s":[100,100]},{"t":80,"s":[7.68,7.68]}]},"r":{"a":0,"k":0},"o":{"a":0,"k":100},"sk":{"a":0,"k":0},"sa":{"a":0,"k":0},"nm":"Transform"}],"nm":"heart dragon","bm":0,"hd":false}],"ip":2,"op":80,"st":-2,"bm":0},{"ddd":0,"ind":4,"ty":4,"nm":"mountain 1","tt":1,"sr":1,"ks":{"p":{"a":1,"k":[{"i":{"x":0.098,"y":1},"o":{"x":0.03,"y":0},"t":0,"s":[1192.466,3227.094,0],"to":[-26.667,-173.333,0],"ti":[26.667,173.333,0]},{"i":{"x":0.903,"y":0.903},"o":{"x":0.167,"y":0.167},"t":40,"s":[1032.466,2187.094,0],"to":[0,0,0],"ti":[0,0,0]},{"i":{"x":0.903,"y":1},"o":{"x":0.917,"y":0},"t":50,"s":[1032.466,2187.094,0],"to":[26.667,173.333,0],"ti":[-26.667,-173.333,0]},{"t":80,"s":[1192.466,3227.094,0]}]},"a":{"a":0,"k":[1068.466,2191.094,0]},"s":{"a":1,"k":[{"i":{"x":[0.098,0.098,0.098],"y":[1,1,1]},"o":{"x":[0.03,0.03,0.03],"y":[0,0,0]},"t":0,"s":[30,30,100]},{"i":{"x":[0.903,0.903,0.903],"y":[1,1,1]},"o":{"x":[0.167,0.167,0.167],"y":[0,0,0]},"t":40,"s":[100,100,100]},{"i":{"x":[0.903,0.903,0.903],"y":[1,1,1]},"o":{"x":[0.917,0.917,0.917],"y":[0,0,0]},"t":50,"s":[100,100,100]},{"t":80,"s":[30,30,100]}]}},"ao":0,"shapes":[{"ty":"gr","it":[{"ind":0,"ty":"sh","ks":{"a":0,"k":{"i":[[0,0],[0,0],[0,0],[0,0],[0,0],[0,0],[0,0],[0,0],[0,0],[0,0]],"o":[[0,0],[0,0],[0,0],[0,0],[0,0],[0,0],[0,0],[0,0],[0,0],[0,0]],"v":[[385.995,-889.059],[509.297,-713.176],[372.824,-571.815],[557.894,-316.423],[353.033,-74.016],[583.216,334.541],[317.637,696.054],[476.866,958.494],[385.995,1049.364],[-583.216,80.152]],"c":true}},"nm":"Path 1","hd":false},{"ty":"fl","c":{"a":0,"k":[0.356999984442,0.356999984442,0.356999984442,1]},"o":{"a":0,"k":100},"r":1,"bm":0,"nm":"Fill 1","hd":false},{"ty":"tr","p":{"a":0,"k":[682.47,2110.941]},"a":{"a":0,"k":[0,0]},"s":{"a":0,"k":[100,100]},"r":{"a":0,"k":0},"o":{"a":0,"k":100},"sk":{"a":0,"k":0},"sa":{"a":0,"k":0},"nm":"Transform"}],"nm":"Group 12","bm":0,"hd":false},{"ty":"gr","it":[{"ind":0,"ty":"sh","ks":{"a":0,"k":{"i":[[0,0],[0,0],[0,0],[0,0]],"o":[[0,0],[0,0],[0,0],[0,0]],"v":[[969.212,80.153],[0,1049.364],[-969.212,80.153],[0,-889.058]],"c":true}},"nm":"Path 1","hd":false},{"ty":"fl","c":{"a":0,"k":[0.102000000898,0.102000000898,0.102000000898,1]},"o":{"a":0,"k":100},"r":1,"bm":0,"nm":"Fill 1","hd":false},{"ty":"tr","p":{"a":0,"k":[1068.466,2110.942]},"a":{"a":0,"k":[0,0]},"s":{"a":0,"k":[100,100]},"r":{"a":0,"k":0},"o":{"a":0,"k":100},"sk":{"a":0,"k":0},"sa":{"a":0,"k":0},"nm":"Transform"}],"nm":"Group 14","bm":0,"hd":false}],"ip":0,"op":19800,"st":0,"bm":0},{"ddd":0,"ind":5,"ty":4,"nm":"mountain2 mask","parent":7,"td":1,"sr":1,"ks":{"p":{"a":0,"k":[246,527,0]},"a":{"a":0,"k":[1544,2320,0]}},"ao":0,"shapes":[{"ty":"gr","it":[{"ind":0,"ty":"sh","ks":{"a":0,"k":{"i":[[89.856,-89.856],[-179.647,-179.402],[0,0],[0,0],[179.646,179.647],[179.647,-179.401],[117.62,0.002]],"o":[[-179.647,179.647],[0,0],[0,0],[179.646,-179.402],[-179.401,-179.402],[-89.79,-89.668],[-117.706,-0.002]],"v":[[-650.176,-560.844],[-650.176,89.456],[0.122,740.489],[650.178,89.456],[650.178,-560.844],[0.122,-561.089],[-324.907,-695.609]],"c":true}},"nm":"path","hd":false},{"ty":"gf","o":{"a":0,"k":100},"r":1,"bm":0,"g":{"p":3,"k":{"a":0,"k":[0,0.161,0.161,0.161,0.5,0.161,0.161,0.161,1,0.161,0.161,0.161]}},"s":{"a":0,"k":[0,741.094]},"e":{"a":0,"k":[-1.859,-688.391]},"t":1,"nm":"Gradient","hd":false},{"ty":"tr","p":{"a":0,"k":[1538.377,2323.593]},"a":{"a":0,"k":[-3.016,739.344]},"s":{"a":1,"k":[{"i":{"x":[0.058,0.058],"y":[1,1]},"o":{"x":[0.183,0.183],"y":[0,0]},"t":0,"s":[7.68,7.68]},{"i":{"x":[0.915,0.915],"y":[1,1]},"o":{"x":[0.167,0.167],"y":[0,0]},"t":40,"s":[100,100]},{"i":{"x":[0.915,0.915],"y":[1,1]},"o":{"x":[0.764,0.764],"y":[0,0]},"t":50,"s":[100,100]},{"t":80,"s":[7.68,7.68]}]},"r":{"a":0,"k":0},"o":{"a":0,"k":100},"sk":{"a":0,"k":0},"sa":{"a":0,"k":0},"nm":"Transform"}],"nm":"heart dragon","bm":0,"hd":false}],"ip":2,"op":80,"st":-2,"bm":0},{"ddd":0,"ind":6,"ty":4,"nm":"mountain 2","tt":1,"sr":1,"ks":{"p":{"a":1,"k":[{"i":{"x":0.098,"y":1},"o":{"x":0.03,"y":0},"t":5,"s":[1636.724,3564.737,0],"to":[26.667,-173.333,0],"ti":[-26.667,173.333,0]},{"i":{"x":0.903,"y":0.903},"o":{"x":0.03,"y":0.03},"t":40,"s":[1796.724,2524.737,0],"to":[0,0,0],"ti":[0,0,0]},{"i":{"x":0.903,"y":1},"o":{"x":0.917,"y":0},"t":50,"s":[1796.724,2524.737,0],"to":[-26.667,173.333,0],"ti":[26.667,-173.333,0]},{"t":80,"s":[1636.724,3564.737,0]}]},"a":{"a":0,"k":[1832.724,2528.737,0]},"s":{"a":1,"k":[{"i":{"x":[0.098,0.098,0.098],"y":[1,1,1]},"o":{"x":[0.03,0.03,0.03],"y":[0,0,0]},"t":5,"s":[30,30,100]},{"i":{"x":[0.903,0.903,0.903],"y":[1,1,1]},"o":{"x":[0.03,0.03,0.03],"y":[0,0,0]},"t":40,"s":[100,100,100]},{"i":{"x":[0.903,0.903,0.903],"y":[1,1,1]},"o":{"x":[0.917,0.917,0.917],"y":[0,0,0]},"t":50,"s":[100,100,100]},{"t":80,"s":[30,30,100]}]}},"ao":0,"shapes":[{"ty":"gr","it":[{"ind":0,"ty":"sh","ks":{"a":0,"k":{"i":[[0,0],[0,0],[0,0],[0,0]],"o":[[0,0],[0,0],[0,0],[0,0]],"v":[[969.211,248.974],[0,1218.186],[-969.212,248.974],[0,-720.237]],"c":true}},"nm":"Path 1","hd":false},{"ty":"fl","c":{"a":0,"k":[0.102000000898,0.102000000898,0.102000000898,1]},"o":{"a":0,"k":100},"r":1,"bm":0,"nm":"Fill 1","hd":false},{"ty":"tr","p":{"a":0,"k":[1832.724,2279.763]},"a":{"a":0,"k":[0,0]},"s":{"a":0,"k":[100,100]},"r":{"a":0,"k":0},"o":{"a":0,"k":100},"sk":{"a":0,"k":0},"sa":{"a":0,"k":0},"nm":"Transform"}],"nm":"Group 13","bm":0,"hd":false}],"ip":0,"op":19800,"st":0,"bm":0},{"ddd":0,"ind":7,"ty":3,"nm":"heart control","sr":1,"ks":{"o":{"a":0,"k":0},"p":{"a":1,"k":[{"i":{"x":0.055,"y":1},"o":{"x":0.106,"y":0},"t":0,"s":[1308,2563,0],"to":[0,-120,0],"ti":[0,120,0]},{"i":{"x":0.055,"y":0.055},"o":{"x":0.333,"y":0.333},"t":40,"s":[1308,1843,0],"to":[0,0,0],"ti":[0,0,0]},{"i":{"x":0.883,"y":1},"o":{"x":0.818,"y":0},"t":50,"s":[1308,1843,0],"to":[0,93.333,0],"ti":[0,-93.333,0]},{"t":80,"s":[1308,2403,0]}]},"a":{"a":0,"k":[50,50,0]}},"ao":0,"ip":-1,"op":19794,"st":-1,"bm":0},{"ddd":0,"ind":8,"ty":4,"nm":"heart mashaladi","parent":7,"sr":1,"ks":{"p":{"a":0,"k":[246,527,0]},"a":{"a":0,"k":[1544,2320,0]}},"ao":0,"shapes":[{"ty":"gr","it":[{"ind":0,"ty":"sh","ks":{"a":0,"k":{"i":[[89.856,-89.856],[-179.647,-179.402],[0,0],[0,0],[179.646,179.647],[179.647,-179.401],[117.62,0.002]],"o":[[-179.647,179.647],[0,0],[0,0],[179.646,-179.402],[-179.401,-179.402],[-89.79,-89.668],[-117.706,-0.002]],"v":[[-650.176,-560.844],[-650.176,89.456],[0.122,740.489],[650.178,89.456],[650.178,-560.844],[0.122,-561.089],[-324.907,-695.609]],"c":true}},"nm":"path","hd":false},{"ty":"gf","o":{"a":0,"k":100},"r":1,"bm":0,"g":{"p":3,"k":{"a":0,"k":[0,0.161,0.161,0.161,0.5,0.161,0.161,0.161,1,0.161,0.161,0.161]}},"s":{"a":0,"k":[0,741.094]},"e":{"a":0,"k":[-1.859,-688.391]},"t":1,"nm":"Gradient","hd":false},{"ty":"tr","p":{"a":0,"k":[1538.377,2323.593]},"a":{"a":0,"k":[-3.016,739.344]},"s":{"a":1,"k":[{"i":{"x":[0.058,0.058],"y":[1,1]},"o":{"x":[0.183,0.183],"y":[0,0]},"t":0,"s":[7.68,7.68]},{"i":{"x":[0.915,0.915],"y":[1,1]},"o":{"x":[0.167,0.167],"y":[0,0]},"t":40,"s":[100,100]},{"i":{"x":[0.915,0.915],"y":[1,1]},"o":{"x":[0.764,0.764],"y":[0,0]},"t":50,"s":[100,100]},{"t":80,"s":[7.68,7.68]}]},"r":{"a":0,"k":0},"o":{"a":0,"k":100},"sk":{"a":0,"k":0},"sa":{"a":0,"k":0},"nm":"Transform"}],"nm":"heart dragon","bm":0,"hd":false}],"ip":2,"op":80,"st":-2,"bm":0}],"markers":[]}